PythonSimpleG4f/LICENSE
PythonSimpleG4f/README.md
PythonSimpleG4f/__init__.py
PythonSimpleG4f/module.py
PythonSimpleG4f/setup.py
simpleg4f-0.1.dist-info/METADATA
simpleg4f-0.1.dist-info/WHEEL
simpleg4f-0.1.dist-info/top_level.txt
simpleg4f-0.1.dist-info/RECORD
