Metadata-Version: 2.1
Name: simpleg4f
Version: 0.1
Summary: asdasd
Author: __token__
Author-email: sponge-bob@krusty-krab.ru
Classifier: Programming Language :: Python :: 3
Classifier: License :: OSI Approved :: MIT License
Classifier: Operating System :: OS Independent
Requires-Python: >=3.13
